temporal_mapper-1.0.2.dist-info/licenses/LICENSE
temporalmapper/__init__.py
temporalmapper/temporal_mapper.py
temporalmapper/utilities.py
temporalmapper/weighted_clustering.py
temporal_mapper-1.0.2.dist-info/METADATA
temporal_mapper-1.0.2.dist-info/WHEEL
temporal_mapper-1.0.2.dist-info/top_level.txt
temporal_mapper-1.0.2.dist-info/RECORD
