Metadata-Version: 2.4
Name: temporal-mapper
Version: 1.0.2
Author-email: Kaleb D Ruscitti <kaleb.ruscitti@uwaterloo.ca>
License: BSD-3-Clause license
Keywords: Mapper,TDA,Morse Theory,Temporal Topic Modeling
License-File: LICENSE
Requires-Dist: numpy
Requires-Dist: matplotlib
Requires-Dist: pandas
Requires-Dist: tqdm
Requires-Dist: scikit-learn
Requires-Dist: scipy
Requires-Dist: networkx
Requires-Dist: numba
Provides-Extra: visualizations
Requires-Dist: datamapplot; extra == "visualizations"
Requires-Dist: datashader; extra == "visualizations"
Requires-Dist: vectorizers; extra == "visualizations"
Dynamic: license-file
